dbsandbox-0.1.0.dist-info/METADATA
dbsandbox-0.1.0.dist-info/WHEEL
dbsandbox-0.1.0.dist-info/licenses/LICENSE
dbsandbox/__init__.py
dbsandbox/dbsandbox.cpython-39-darwin.so
dbsandbox-0.1.0.dist-info/RECORD
