Metadata-Version: 2.4
Name: dbsandbox
Version: 0.1.0
License-File: LICENSE
Summary: Create test databases in 1 line of code
Author-email: Michael <kkodokkushi@gmail.com>
License: MIT
Requires-Python: >=3.8
